aiplanet/__init__.py
aiplanet/cli.py
aiplanet/commands/add.py
aiplanet/commands/build.py
aiplanet/commands/gen.py
aiplanet/commands/migrate.py
aiplanet/commands/remove.py
aiplanet/commands/run.py
aiplanet/templates/README.md.jinja
aiplanet/templates/alembic.ini.jinja
aiplanet/templates/constant.py.jinja
aiplanet/templates/core/config.py.jinja
aiplanet/templates/core/database.py.jinja
aiplanet/templates/core/logging.py.jinja
aiplanet/templates/core/security.py.jinja
aiplanet/templates/docker/Dockerfile.jinja
aiplanet/templates/docker/docker-compose.yaml.jinja
aiplanet/templates/env.jinja
aiplanet/templates/exception.py.jinja
aiplanet/templates/gitignore.jinja
aiplanet/templates/job.py.jinja
aiplanet/templates/main.py.jinja
aiplanet/templates/middleware.py.jinja
aiplanet/templates/migrations/alembic.ini.jinja
aiplanet/templates/migrations/env.py.jinja
aiplanet/templates/migrations/script.py.mako.jinja
aiplanet/templates/model.py.jinja
aiplanet/templates/pyproject.toml.jinja
aiplanet/templates/router.py.jinja
aiplanet/templates/schema.py.jinja
aiplanet/templates/service.py.jinja
aiplanet/templates/util.py.jinja
aiplanet/utils/console.py
aiplanet/utils/filesystem.py
aiplanet/utils/templates.py
aiplanet-1.0.0.dist-info/METADATA
aiplanet-1.0.0.dist-info/WHEEL
aiplanet-1.0.0.dist-info/entry_points.txt
aiplanet-1.0.0.dist-info/RECORD
