Metadata-Version: 2.3
Name: aiplanet
Version: 1.0.0
Summary: CLI tool for generating FastAPI project boilerplate
Author: Your Name
Author-email: your.email@example.com
Requires-Python: >=3.10,<4.0
Classifier: Programming Language :: Python :: 3
Classifier: Programming Language :: Python :: 3.10
Classifier: Programming Language :: Python :: 3.11
Classifier: Programming Language :: Python :: 3.12
Classifier: Programming Language :: Python :: 3.13
Requires-Dist: click (>=8.1.3,<9.0.0)
Requires-Dist: colorama (>=0.4.6,<0.5.0)
Requires-Dist: jinja2 (>=3.1.2,<4.0.0)
Requires-Dist: pydantic (>=2.0.0,<3.0.0)
Requires-Dist: pyyaml (>=6.0.1,<7.0.0)
Requires-Dist: questionary (>=1.10.0,<2.0.0)
Requires-Dist: rich (>=13.3.5,<14.0.0)
Requires-Dist: shellingham (>=1.5.0,<2.0.0)
Requires-Dist: typer (>=0.9.0,<0.10.0)
